README.md
setup.cfg
setup.py
ergonomics/__init__.py
ergonomics/owas.py
ergonomics/reba.py
ergonomics/utils.py
ergonomics_metrics.egg-info/PKG-INFO
ergonomics_metrics.egg-info/SOURCES.txt
ergonomics_metrics.egg-info/dependency_links.txt
ergonomics_metrics.egg-info/top_level.txt