Metadata-Version: 2.1
Name: ergonomics-metrics
Version: 0.4.3
Summary: Ergonomics metrics
Home-page: https://github.com/rs9000/ergonomics
Author: Rosario Di Carlo
Author-email: rs.dicarlo@gmail.com
License: UNKNOWN
Platform: UNKNOWN
Classifier: Programming Language :: Python :: 3
Classifier: License :: OSI Approved :: MIT License
Classifier: Operating System :: OS Independent
